imageatlas/__init__.py
imageatlas/clustering/__init__.py
imageatlas/clustering/base.py
imageatlas/clustering/factory.py
imageatlas/clustering/gmm.py
imageatlas/clustering/hdbscan_clustering.py
imageatlas/clustering/kmeans.py
imageatlas/core/__init__.py
imageatlas/core/clusterer.py
imageatlas/core/results.py
imageatlas/features/__init__.py
imageatlas/features/adapter.py
imageatlas/features/batch.py
imageatlas/features/cache.py
imageatlas/features/loaders.py
imageatlas/features/metadata.py
imageatlas/features/pipeline.py
imageatlas/features/extractors/__init__.py
imageatlas/features/extractors/base.py
imageatlas/features/extractors/clip.py
imageatlas/features/extractors/convnext.py
imageatlas/features/extractors/dinov2.py
imageatlas/features/extractors/efficientnet.py
imageatlas/features/extractors/factory.py
imageatlas/features/extractors/mobilenet.py
imageatlas/features/extractors/resnet.py
imageatlas/features/extractors/swin.py
imageatlas/features/extractors/vgg.py
imageatlas/features/extractors/vit.py
imageatlas/reduction/__init__.py
imageatlas/reduction/base.py
imageatlas/reduction/factory.py
imageatlas/reduction/pca.py
imageatlas/reduction/tsne.py
imageatlas/reduction/umap_reducer.py
imageatlas/visualization/__init__.py
imageatlas/visualization/grids.py
imageatlas-0.1.1.dist-info/licenses/LICENSE
imageatlas-0.1.1.dist-info/METADATA
imageatlas-0.1.1.dist-info/WHEEL
imageatlas-0.1.1.dist-info/top_level.txt
imageatlas-0.1.1.dist-info/RECORD
