Metadata-Version: 2.4
Name: imageatlas
Version: 0.1.1
Summary: ImageAtlas: A toolkit for organizing, cleaning and analysing your image datasets.
Author-email: Ahmad Javed <ahmadjaved97@gmail.com>
Maintainer-email: Ahmad Javed <ahmadjaved97@gmail.com>
License: MIT License
Project-URL: Homepage, https://github.com/ahmadjaved97/imageatlas
Project-URL: Documentation, https://github.com/ahmadjaved97/imageatlas
Project-URL: Repository, https://github.com/ahmadjaved97/imageatlas
Project-URL: Issues, https://github.com/ahmadjaved97/imageatlas/issues
Project-URL: Changelog, https://github.com/ahmadjaved97/imageatlas/blob/main/CHANGELOG.md
Keywords: machine-learning,computer-vision,clustering,embeddings,feature-extraction,dataset-visualization,deep-learning,image-processing,data-science,pytorch
Classifier: Development Status :: 4 - Beta
Classifier: Intended Audience :: Developers
Classifier: Intended Audience :: Science/Research
Classifier: License :: OSI Approved :: MIT License
Classifier: Operating System :: OS Independent
Classifier: Programming Language :: Python :: 3
Classifier: Programming Language :: Python :: 3.10
Classifier: Programming Language :: Python :: 3.11
Classifier: Programming Language :: Python :: 3.12
Classifier: Topic :: Scientific/Engineering :: Artificial Intelligence
Classifier: Topic :: Scientific/Engineering :: Image Recognition
Classifier: Topic :: Scientific/Engineering :: Visualization
Requires-Python: >=3.8
License-File: LICENSE
Requires-Dist: torch>=2.0.1
Requires-Dist: torchvision>=0.15.2
Requires-Dist: numpy>=1.24.2
Requires-Dist: Pillow>=9.5.0
Requires-Dist: opencv-python>=4.8.0.74
Requires-Dist: scikit-learn>=1.3.0
Requires-Dist: tqdm>=4.67.1
Requires-Dist: h5py>=3.15.1
Requires-Dist: pandas>=2.3.3
Provides-Extra: full
Requires-Dist: umap-learn; extra == "full"
Requires-Dist: hdbscan; extra == "full"
Requires-Dist: openpyxl; extra == "full"
Dynamic: license-file
